lambda_lift/__init__.py
lambda_lift/cli_main.py
lambda_lift/exceptions.py
lambda_lift/py.typed
lambda_lift/config/__init__.py
lambda_lift/config/enums.py
lambda_lift/config/exceptions.py
lambda_lift/config/file_matching.py
lambda_lift/config/parser.py
lambda_lift/config/registry.py
lambda_lift/config/single_lambda.py
lambda_lift/deployment/__init__.py
lambda_lift/deployment/aws.py
lambda_lift/deployment/exceptions.py
lambda_lift/packer/__init__.py
lambda_lift/packer/cache.py
lambda_lift/packer/packaging.py
lambda_lift/packer/pip.py
lambda_lift/packer/zip.py
lambda_lift/utils/__init__.py
lambda_lift/utils/cli_tools.py
lambda_lift/utils/git.py
lambda_lift/utils/hashing.py
lambda_lift-0.0.12.dist-info/METADATA
lambda_lift-0.0.12.dist-info/WHEEL
lambda_lift-0.0.12.dist-info/entry_points.txt
lambda_lift-0.0.12.dist-info/licenses/LICENSE
lambda_lift-0.0.12.dist-info/RECORD
