Metadata-Version: 2.3
Name: lambda-lift
Version: 0.0.12
Summary: An AWS Lambda packager
Project-URL: Homepage, https://github.com/a-kazakov/lambda-lift
Project-URL: Issues, https://github.com/a-kazakov/lambda-lift/issues
Author-email: Artem Kazakov <opensource@akazakov.net>
License-File: LICENSE
Classifier: License :: OSI Approved :: MIT License
Classifier: Operating System :: OS Independent
Classifier: Programming Language :: Python :: 3
Requires-Python: >=3.10
Requires-Dist: boto3
Requires-Dist: click
Requires-Dist: repro-zipfile
Requires-Dist: rich
